ghastoolkit/__init__.py
ghastoolkit/__main__.py
ghastoolkit/errors.py
ghastoolkit/billing/__main__.py
ghastoolkit/codeql/__init__.py
ghastoolkit/codeql/__main__.py
ghastoolkit/codeql/cli.py
ghastoolkit/codeql/consts.py
ghastoolkit/codeql/databases.py
ghastoolkit/codeql/results.py
ghastoolkit/codeql/dataextensions/__init__.py
ghastoolkit/codeql/dataextensions/__main__.py
ghastoolkit/codeql/dataextensions/ext.py
ghastoolkit/codeql/dataextensions/models.py
ghastoolkit/codeql/packs/__init__.py
ghastoolkit/codeql/packs/__main__.py
ghastoolkit/codeql/packs/pack.py
ghastoolkit/codeql/packs/packs.py
ghastoolkit/octokit/__init__.py
ghastoolkit/octokit/advisories.py
ghastoolkit/octokit/billing.py
ghastoolkit/octokit/clearlydefined.py
ghastoolkit/octokit/codescanning.py
ghastoolkit/octokit/dependabot.py
ghastoolkit/octokit/dependencygraph.py
ghastoolkit/octokit/enterprise.py
ghastoolkit/octokit/github.py
ghastoolkit/octokit/octokit.py
ghastoolkit/octokit/repository.py
ghastoolkit/octokit/secretscanning.py
ghastoolkit/octokit/graphql/__init__.py
ghastoolkit/secretscanning/__init__.py
ghastoolkit/secretscanning/secretalerts.py
ghastoolkit/supplychain/__init__.py
ghastoolkit/supplychain/__main__.py
ghastoolkit/supplychain/advisories.py
ghastoolkit/supplychain/dependencies.py
ghastoolkit/supplychain/dependency.py
ghastoolkit/supplychain/dependencyalert.py
ghastoolkit/supplychain/licensing.py
ghastoolkit/utils/__init__.py
ghastoolkit/utils/cache.py
ghastoolkit/utils/cli.py
ghastoolkit-0.18.1.dist-info/licenses/LICENSE
ghastoolkit-0.18.1.dist-info/METADATA
ghastoolkit-0.18.1.dist-info/WHEEL
ghastoolkit-0.18.1.dist-info/top_level.txt
ghastoolkit-0.18.1.dist-info/RECORD
