Metadata-Version: 2.4
Name: ghastoolkit
Version: 0.18.1
Summary: GitHub Advanced Security Python Toolkit
Author: GeekMasher
Project-URL: Homepage, https://github.com/GeekMasher/ghastoolkit
Project-URL: Bug Tracker, https://github.com/GeekMasher/ghastoolkit/issues
Classifier: Development Status :: 4 - Beta
Classifier: License :: OSI Approved :: MIT License
Classifier: Programming Language :: Python :: 3
Classifier: Programming Language :: Python :: 3.10
Classifier: Programming Language :: Python :: 3.11
Classifier: Programming Language :: Python :: 3.12
Classifier: Programming Language :: Python :: 3.13
Classifier: Operating System :: OS Independent
Requires-Python: >=3.10
License-File: LICENSE
Requires-Dist: pyyaml==6.0.3
Requires-Dist: ratelimit==2.2.1
Requires-Dist: requests>=2.32.4
Requires-Dist: semantic-version==2.10.0
Dynamic: license-file
